README.rst
parsesetup.py
setup.py
parsesetup.egg-info/PKG-INFO
parsesetup.egg-info/SOURCES.txt
parsesetup.egg-info/dependency_links.txt
parsesetup.egg-info/requires.txt
parsesetup.egg-info/top_level.txt