Metadata-Version: 1.2
Name: parsesetup
Version: 0.0.1
Summary: Parses setup.py files
Home-page: http://github.com/benfred/parsesetup/
Author: Ben Frederickson
Author-email: ben@benfrederickson.com
License: MIT
Platform: UNKNOWN
Classifier: Development Status :: 3 - Alpha
Classifier: Programming Language :: Python :: 3
Classifier: Intended Audience :: Developers
Classifier: License :: OSI Approved :: MIT License
Classifier: Topic :: Software Development :: Libraries
Classifier: Topic :: Utilities
Requires-Python: >=3.5
